glue_ginga/__init__.py
glue_ginga/conftest.py
glue_ginga/version.py
glue_ginga/plugins/Glue.py
glue_ginga/plugins/__init__.py
glue_ginga/qt/__init__.py
glue_ginga/qt/layer_artist.py
glue_ginga/qt/mouse_modes.py
glue_ginga/qt/utils.py
glue_ginga/qt/viewer_widget.py
glue_ginga/qt/tests/__init__.py
glue_ginga/qt/tests/test_viewer_widget.py
glue_ginga/tests/__init__.py
glue_ginga-0.2.dist-info/DESCRIPTION.rst
glue_ginga-0.2.dist-info/METADATA
glue_ginga-0.2.dist-info/RECORD
glue_ginga-0.2.dist-info/WHEEL
glue_ginga-0.2.dist-info/entry_points.txt
glue_ginga-0.2.dist-info/metadata.json
glue_ginga-0.2.dist-info/top_level.txt
