Metadata-Version: 2.0
Name: glue-ginga
Version: 0.2
Summary: Ginga viewer plugin for glue
Home-page: https://github.com/ejeschke/glue-ginga
Author: Eric Jeschke, Tom Robitaille
Author-email: eric@naoj.org, thomas.robitaille@gmail.com
License: UNKNOWN
Platform: UNKNOWN
Requires-Dist: ginga (>=2.6.1)
Requires-Dist: glue-core (>=0.11.0)
